<mvc:View
    xmlns:core="sap.ui.core"
    xmlns:mvc="sap.ui.core.mvc"
    xmlns="sap.m"
    xmlns:table="sap.ui.table"
    xmlns:rowmodes="sap.ui.table.rowmodes"
    width="100%"
    height="100%"
    displayBlock="true"
    controllerName="bix.card.actualPipelineDetailTable.Main"
>
    <Panel
        expandable="false"
        expanded="true"
        width="auto"
        
    >
        <headerToolbar>
            <OverflowToolbar>
                <ToolbarSpacer />
                <Select
                    change=".onUiChange"
                    width="30%"
                    items="{path: 'SelectModel>/'}"
                >
                    <items>
                        <core:ListItem
                            key="{SelectModel>key}"
                            text="{SelectModel>name}"
                        />
                    </items>
                </Select>
            </OverflowToolbar>
        </headerToolbar>
        <content>
        <VBox fitContainer="true">
            <table:Table
                id="actualPipelineDetailTable1"
                rows="{path:'plUiTableModel>/'}"
                selectionMode="None"
                class="custom-table-container custom-table-container-fixed custom-table-header custom-table-body custom-table-first-emphasis custom-uiTable-selection custom-inherit-height custom-table-rounding-border "
                visible="{=${uIModel>/tableKind} === 'stage'}"
                busyIndicatorDelay="0"
                fixedColumnCount="2"
            >

            <table:layoutData>
                        <FlexItemData growFactor="1"/>
                    </table:layoutData>

                <table:extension>
                    <OverflowToolbar style="Clear">
                        <ToolbarSpacer />                        
                        <Select
                            change=".onUiChange"
                            width="30%"                            
                            selectedKey="{uIModel>/tableKind}"
                            items="{path: 'SelectModel>/'}"
                        >
                            <items>
                                <core:ListItem
                                    key="{SelectModel>key}"
                                    text="{SelectModel>name}"
                                />
                            </items>
                        </Select>
                    </OverflowToolbar>
                </table:extension>

                <table:columns>
                    <table:Column
                        hAlign="Center"
                        headerSpan="2"
                        autoResizable="true"
                        width="5rem"
                    >
                        <Label
                            text="단위/억"
                            wrapping="true"
                        />
                        <table:template>
                            <Text
                                text="{plUiTableModel>type1}"
                                wrapping="false"
                                width="100%"
                                textAlign="Center"
                            />
                        </table:template>
                    </table:Column>
                    <table:Column
                        hAlign="Center"
                        autoResizable="true"
                        width="5rem"
                    >
                        <Label
                            text="단위/억"
                            wrapping="true"
                        />
                        <table:template>
                            <Text
                                text="{plUiTableModel>type2}"
                                wrapping="false"
                                width="100%"
                                textAlign="Center"
                            />
                        </table:template>
                    </table:Column>
                    <table:Column
                        hAlign="Center"
                        autoResizable="true"
                        width="7rem"
                    >
                        <Label
                            text="Total"
                            wrapping="true"
                        />
                        <table:template>
                            <Text
                                text="{plUiTableModel>total}"
                                wrapping="false"
                                width="100%"
                                textAlign="Center"
                            />
                        </table:template>
                    </table:Column>
                    <table:Column
                        hAlign="Center"
                        autoResizable="true"
                        width="7rem"
                    >
                        <Label
                            text="Lead"
                            wrapping="true"
                        />
                        <table:template>
                            <Text
                                text="{plUiTableModel>lead}"
                                wrapping="false"
                                width="100%"
                                textAlign="Center"
                            />
                        </table:template>
                    </table:Column>
                    <table:Column
                        hAlign="Center"
                        autoResizable="true"
                        width="7rem"
                    >
                        <Label
                            text="Identified"
                            wrapping="true"
                        />
                        <table:template>
                            <Text
                                text="{plUiTableModel>identified}"
                                wrapping="false"
                                width="100%"
                                textAlign="Center"
                            />
                        </table:template>
                    </table:Column>
                    <table:Column
                        hAlign="Center"
                        autoResizable="true"
                        width="7rem"
                    >
                        <Label
                            text="Validated"
                            wrapping="true"
                        />
                        <table:template>
                            <Text
                                text="{plUiTableModel>validated}"
                                wrapping="false"
                                width="100%"
                                textAlign="Center"
                            />
                        </table:template>
                    </table:Column>
                    <table:Column
                        hAlign="Center"
                        autoResizable="true"
                        width="7rem"
                    >
                        <Label
                            text="Qualified"
                            wrapping="true"
                        />
                        <table:template>
                            <Text
                                text="{plUiTableModel>qualified}"
                                wrapping="false"
                                width="100%"
                                textAlign="Center"
                            />
                        </table:template>
                    </table:Column>
                    <table:Column
                        hAlign="Center"
                        autoResizable="true"
                        width="7rem"
                    >
                        <Label
                            text="Negotiated"
                            wrapping="true"
                        />
                        <table:template>
                            <Text
                                text="{plUiTableModel>negotiated}"
                                wrapping="false"
                                width="100%"
                                textAlign="Center"
                            />
                        </table:template>
                    </table:Column>
                    <table:Column
                        hAlign="Center"
                        autoResizable="true"
                        width="7rem"
                    >
                        <Label
                            text="Contracted"
                            wrapping="true"
                        />
                        <table:template>
                            <Text
                                text="{plUiTableModel>contracted}"
                                wrapping="false"
                                width="100%"
                                textAlign="Center"
                            />
                        </table:template>
                    </table:Column>
                    <table:Column
                        hAlign="Center"
                        autoResizable="true"
                        width="7rem"
                    >
                        <Label
                            text="Deal Lost"
                            wrapping="true"
                        />
                        <table:template>
                            <Text
                                text="{plUiTableModel>dealLost}"
                                wrapping="false"
                                width="100%"
                                textAlign="Center"
                            />
                        </table:template>
                    </table:Column>
                    <table:Column
                        hAlign="Center"
                        autoResizable="true"
                        width="7rem"
                    >
                        <Label
                            text="Deselected"
                            wrapping="true"
                        />
                        <table:template>
                            <Text
                                text="{plUiTableModel>deselected}"
                                wrapping="false"
                                width="100%"
                                textAlign="Center"
                            />
                        </table:template>
                    </table:Column>
                </table:columns>
            </table:Table>

            <table:Table
                id="actualPipelineDetailTable2"
                rows="{path:'plUiTableModel>/'}"
                selectionMode="None"
                class="custom-table-container custom-table-container-fixed custom-table-header custom-table-body custom-table-first-emphasis custom-uiTable-selection custom-inherit-height custom-table-rounding-border  custom-table-first-emphasis custom-uiTable-selection custom-inherit-height custom-selection-radius"
                visible="{=${uIModel>/tableKind} === 'month'}"
                busyIndicatorDelay="0"
                fixedColumnCount="2"
            >

            <table:layoutData>
                        <FlexItemData growFactor="1"/>
                    </table:layoutData>

                <table:extension>
                    <OverflowToolbar style="Clear">
                        <ToolbarSpacer />                        
                        <Select
                            change=".onUiChange"
                            width="30%"                            
                            selectedKey="{uIModel>/tableKind}"
                            items="{path: 'SelectModel>/'}"
                        >
                            <items>
                                <core:ListItem
                                    key="{SelectModel>key}"
                                    text="{SelectModel>name}"
                                />
                            </items>
                        </Select>
                    </OverflowToolbar>
                </table:extension>

                <table:columns>
                    <table:Column
                        hAlign="Center"
                        headerSpan="2"
                        autoResizable="true"
                        width="5rem"
                    >
                        <Label
                            text="단위/억"
                            wrapping="true"
                        />
                        <table:template>
                            <Text
                                text="{plUiTableModel>type1}"
                                wrapping="false"
                                width="100%"
                                textAlign="Center"
                            />
                        </table:template>
                    </table:Column>

                    <table:Column
                        hAlign="Center"
                        autoResizable="true"
                        width="5rem"
                    >
                        <Label
                            text="단위/억"
                            wrapping="true"
                        />
                        <table:template>
                            <Text
                                text="{plUiTableModel>type2}"
                                wrapping="false"
                                width="100%"
                                textAlign="Center"
                            />
                        </table:template>
                    </table:Column>

                    <table:Column
                        hAlign="Center"
                        autoResizable="true"
                        width="7rem"
                    >
                        <Label
                            text="5월"
                            wrapping="true"
                        />
                        <table:template>
                            <Text
                                text="{plUiTableModel>total}"
                                wrapping="false"
                                width="100%"
                                textAlign="Center"
                            />
                        </table:template>
                    </table:Column>

                    <table:Column
                        hAlign="Center"
                        autoResizable="true"
                        width="7rem"
                    >
                        <Label
                            text="6월"
                            wrapping="true"
                        />
                        <table:template>
                            <Text
                                text="{plUiTableModel>lead}"
                                wrapping="false"
                                width="100%"
                                textAlign="Center"
                            />
                        </table:template>
                    </table:Column>

                    <table:Column
                        hAlign="Center"
                        autoResizable="true"
                        width="7rem"
                    >
                        <Label
                            text="7월"
                            wrapping="true"
                        />
                        <table:template>
                            <Text
                                text="{plUiTableModel>identified}"
                                wrapping="false"
                                width="100%"
                                textAlign="Center"
                            />
                        </table:template>
                    </table:Column>

                    <table:Column
                        hAlign="Center"
                        autoResizable="true"
                        width="7rem"
                    >
                        <Label
                            text="8월"
                            wrapping="true"
                        />
                        <table:template>
                            <Text
                                text="{plUiTableModel>validated}"
                                wrapping="false"
                                width="100%"
                                textAlign="Center"
                            />
                        </table:template>
                    </table:Column>

                    <table:Column
                        hAlign="Center"
                        autoResizable="true"
                        width="7rem"
                    >
                        <Label
                            text="9월"
                            wrapping="true"
                        />
                        <table:template>
                            <Text
                                text="{plUiTableModel>qualified}"
                                wrapping="false"
                                width="100%"
                                textAlign="Center"
                            />
                        </table:template>
                    </table:Column>

                    <table:Column
                        hAlign="Center"
                        autoResizable="true"
                        width="7rem"
                    >
                        <Label
                            text="10월"
                            wrapping="true"
                        />
                        <table:template>
                            <Text
                                text="{plUiTableModel>contracted}"
                                wrapping="false"
                                width="100%"
                                textAlign="Center"
                            />
                        </table:template>
                    </table:Column>

                    <table:Column
                        hAlign="Center"
                        autoResizable="true"
                        width="7rem"
                    >
                        <Label
                            text="11월"
                            wrapping="true"
                        />
                        <table:template>
                            <Text
                                text="{plUiTableModel>dealLost}"
                                wrapping="false"
                                width="100%"
                                textAlign="Center"
                            />
                        </table:template>
                    </table:Column>

                    <table:Column
                        hAlign="Center"
                        autoResizable="true"
                        width="7rem"
                    >
                        <Label
                            text="12월"
                            wrapping="true"
                        />
                        <table:template>
                            <Text
                                text="{plUiTableModel>dealLost}"
                                wrapping="false"
                                width="100%"
                                textAlign="Center"
                            />
                        </table:template>
                    </table:Column>
                </table:columns>
            </table:Table>

            <table:Table
                id="actualPipelineDetailTable3"
                rows="{path:'plUiTableModel>/'}"
                selectionMode="None"
                class="custom-table-container custom-table-container-fixed custom-table-header custom-table-body custom-table-first-emphasis custom-uiTable-selection custom-inherit-height custom-table-rounding-border  custom-table-first-emphasis custom-uiTable-selection custom-inherit-height custom-selection-radius"
                visible="{=${uIModel>/tableKind} === 'money'}"
                busyIndicatorDelay="0"
                fixedColumnCount="2"
            >

            <table:layoutData>
                        <FlexItemData growFactor="1"/>
                    </table:layoutData>

                <table:extension>
                    <OverflowToolbar style="Clear">
                        <ToolbarSpacer />                        
                        <Select
                            change=".onUiChange"
                            width="30%"                            
                            selectedKey="{uIModel>/tableKind}"
                            items="{path: 'SelectModel>/'}"
                        >
                            <items>
                                <core:ListItem
                                    key="{SelectModel>key}"
                                    text="{SelectModel>name}"
                                />
                            </items>
                        </Select>
                    </OverflowToolbar>
                </table:extension>

                <table:columns>
                    <table:Column
                        hAlign="Center"
                        headerSpan="2"
                        autoResizable="true"
                        width="5rem"
                    >
                        <Label
                            text="단위/억"
                            wrapping="true"
                        />
                        <table:template>
                            <Text
                                text="{plUiTableModel>type1}"
                                wrapping="false"
                                width="100%"
                                textAlign="Center"
                            />
                        </table:template>
                    </table:Column>

                    <table:Column
                        hAlign="Center"
                        autoResizable="true"
                        width="5rem"
                    >
                        <Label
                            text="단위/억"
                            wrapping="true"
                        />
                        <table:template>
                            <Text
                                text="{plUiTableModel>type2}"
                                wrapping="false"
                                width="100%"
                                textAlign="Center"
                            />
                        </table:template>
                    </table:Column>
                    
                    <table:Column
                        hAlign="Center"
                        autoResizable="true"
                        width="7rem"
                    >
                        <Label
                            text="100억 이상"
                            wrapping="true"
                        />
                        <table:template>
                            <Text
                                text="{plUiTableModel>lead}"
                                wrapping="false"
                                width="100%"
                                textAlign="Center"
                            />
                        </table:template>
                    </table:Column>

                    <table:Column
                        hAlign="Center"
                        autoResizable="true"
                        width="7rem"
                    >
                        <Label
                            text="50억~100억"
                            wrapping="true"
                        />
                        <table:template>
                            <Text
                                text="{plUiTableModel>identified}"
                                wrapping="false"
                                width="100%"
                                textAlign="Center"
                            />
                        </table:template>
                    </table:Column>

                    <table:Column
                        hAlign="Center"
                        autoResizable="true"
                        width="7rem"
                    >
                        <Label
                            text="30억~50억"
                            wrapping="true"
                        />
                        <table:template>
                            <Text
                                text="{plUiTableModel>validated}"
                                wrapping="false"
                                width="100%"
                                textAlign="Center"
                            />
                        </table:template>
                    </table:Column>

                    <table:Column
                        hAlign="Center"
                        autoResizable="true"
                        width="7rem"
                    >
                        <Label
                            text="10억~30억"
                            wrapping="true"
                        />
                        <table:template>
                            <Text
                                text="{plUiTableModel>qualified}"
                                wrapping="false"
                                width="100%"
                                textAlign="Center"
                            />
                        </table:template>
                    </table:Column>

                    <table:Column
                        hAlign="Center"
                        autoResizable="true"
                        width="7rem"
                    >
                        <Label
                            text="5억~10억"
                            wrapping="true"
                        />
                        <table:template>
                            <Text
                                text="{plUiTableModel>contracted}"
                                wrapping="false"
                                width="100%"
                                textAlign="Center"
                            />
                        </table:template>
                    </table:Column>

                    <table:Column
                        hAlign="Center"
                        autoResizable="true"
                        width="7rem"
                    >
                        <Label
                            text="1억~5억"
                            wrapping="true"
                        />
                        <table:template>
                            <Text
                                text="{plUiTableModel>dealLost}"
                                wrapping="false"
                                width="100%"
                                textAlign="Center"
                            />
                        </table:template>
                    </table:Column>

                    <table:Column
                        hAlign="Center"
                        autoResizable="true"
                        width="7rem"
                    >
                        <Label
                            text="1억 미만"
                            wrapping="true"
                        />
                        <table:template>
                            <Text
                                text="{plUiTableModel>dealLost}"
                                wrapping="false"
                                width="100%"
                                textAlign="Center"
                            />
                        </table:template>
                    </table:Column>
                </table:columns>
            </table:Table>
        </VBox>
        </content>
    </Panel>
</mvc:View>
